README
setup.py
EGEGrouper.egg-info/PKG-INFO
EGEGrouper.egg-info/SOURCES.txt
EGEGrouper.egg-info/dependency_links.txt
EGEGrouper.egg-info/entry_points.txt
EGEGrouper.egg-info/requires.txt
EGEGrouper.egg-info/top_level.txt
egegrouper/__init__.py
egegrouper/base_model.py
egegrouper/base_views.py
egegrouper/controller.py
egegrouper/exporters.py
egegrouper/glob.py
egegrouper/igrouper.py
egegrouper/importers.py
egegrouper/plot_views.py
egegrouper/simple_signal.py
egegrouper/sme.py
egegrouper/sme_json.py
egegrouper/sme_sqlite3.py
egegrouper/sqlite3_model.py
egegrouper/stats_controller.py
egegrouper/stats_model.py
egegrouper/text_views.py
egegrouper/tk_views.py
egegrouper/tk_widgets.py
egegrouper/tkgrouper.py