Metadata-Version: 1.1
Name: EGEGrouper
Version: 0.7.0
Summary: Tool for grouping EGEG examinations
Home-page: https://bitbucket.org/aleneus/egegrouper
Author: Aleksandr Popov
Author-email: aleneus@gmail.com
License: GPLv3
Keywords: electrophysiology electrogastrography electrogastroenterography biosignal storage dataset
Platform: UNKNOWN
Classifier: Development Status :: 4 - Beta
Classifier: Environment :: Console
Classifier: Environment :: X11 Applications
Classifier: Intended Audience :: Science/Research
Classifier: Intended Audience :: Developers
Classifier: License :: OSI Approved :: GNU General Public License v3 (GPLv3)
Classifier: Operating System :: POSIX :: Linux
Classifier: Operating System :: Microsoft :: Windows
Classifier: Programming Language :: Python :: 3
Classifier: Topic :: Scientific/Engineering :: Bio-Informatics
